async_kinesis_client/__init__.py
async_kinesis_client/boto_exceptions.py
async_kinesis_client/dynamodb.py
async_kinesis_client/kinesis_consumer.py
async_kinesis_client/kinesis_producer.py
async_kinesis_client/retriable_operations.py
async_kinesis_client-0.2.14.dist-info/LICENSE
async_kinesis_client-0.2.14.dist-info/METADATA
async_kinesis_client-0.2.14.dist-info/WHEEL
async_kinesis_client-0.2.14.dist-info/top_level.txt
async_kinesis_client-0.2.14.dist-info/RECORD
