Metadata-Version: 2.1
Name: async-kinesis-client
Version: 0.2.14
Summary: Asynchronous Python client for AWS Kinesis
Home-page: https://github.com/whale2/async-kinesis-client
Author: Nikita Makeev
Author-email: whale2.box@gmail.com
License: MIT
Platform: UNKNOWN
Classifier: Development Status :: 3 - Alpha
Classifier: Intended Audience :: Developers
Classifier: License :: OSI Approved :: MIT License
Classifier: Natural Language :: English
Classifier: Programming Language :: Python :: 3
Classifier: Programming Language :: Python :: 3.7
Classifier: Topic :: Internet
Classifier: Topic :: Software Development :: Libraries
Requires-Dist: aioboto3 (>=6.0.1)
Requires-Dist: multidict (>=4.5.2)
